Metadata-Version: 2.1
Name: church-fundraising
Version: 0.1.0
Summary: A library for managing products and transactions for church fundraising
Home-page: https://github.com/Rubanthirukumaran/Cpp-library.git
Author: Ruban Thirukumaran
Author-email: rubanthirukumaran@gmail.com
Classifier: Programming Language :: Python :: 3
Classifier: License :: OSI Approved :: MIT License
Classifier: Operating System :: OS Independent
Requires-Python: >=3.6
License-File: LICENSE
